{
  "accentColor": "{{appsmith.theme.colors.primaryColor}}",
  "allowScroll": false,
  "animateLoading": true,
  "borderRadius": "{{appsmith.theme.borderRadius.appBorderRadius}}",
  "bottomRow": 106,
  "boxShadow": "{{appsmith.theme.boxShadow.appBoxShadow}}",
  "chartData": {
    "m7eji81ftj": {
      "data": [
        {
          "x": "Product1",
          "y": 20000
        },
        {
          "x": "Product2",
          "y": 22000
        },
        {
          "x": "Product3",
          "y": 32000
        }
      ],
      "seriesName": "2023"
    }
  },
  "chartName": "Sales Report",
  "chartType": "CUSTOM_ECHART",
  "customEChartConfig": "{{ ((chartType) => ( \n{\n  title: {\n    text: 'Water flow',\n    subtext: 'Sensor Data'\n  },\n  tooltip: {\n    trigger: 'axis',\n    axisPointer: {\n      type: 'cross'\n    }\n  },\n  toolbox: {\n    show: true,\n    feature: {\n      saveAsImage: {}\n    }\n  },\n  xAxis: {\n    type: 'category',\n    boundaryGap: false,\n    // prettier-ignore\n    data: Tb_Telemetry_Water_Flow_Fetch.data.totalLiters.map(totalLiters => totalLiters.ts)\n  },\n  yAxis: {\n    type: 'value',\n    axisLabel: {\n      formatter: '{value} W'\n    },\n    axisPointer: {\n      snap: true\n    }\n  },\n  visualMap: {\n    show: false,\n    dimension: 0,\n    pieces: [\n      {\n        lte: 6,\n        color: 'green'\n      },\n      {\n        gt: 6,\n        lte: 8,\n        color: 'red'\n      },\n      {\n        gt: 8,\n        lte: 14,\n        color: 'green'\n      },\n      {\n        gt: 14,\n        lte: 17,\n        color: 'red'\n      },\n      {\n        gt: 17,\n        color: 'green'\n      }\n    ]\n  },\n  series: [\n    {\n      name: 'Water flow',\n      type: 'line',\n      smooth: true,\n      // prettier-ignore\n      data: Tb_Telemetry_Water_Flow_Fetch.data.totalLiters.map(totalLiters => totalLiters.value)\n    }\n  ]\n}\n))(ChartWater.chartType) }}",
  "customFusionChartConfig": {
    "dataSource": {
      "chart": {
        "alignCaptionWithCanvas": 1,
        "canvasPadding": "0",
        "caption": "Sales Report",
        "captionAlignment": "center",
        "captionFontColor": "#231F20",
        "captionFontSize": "24",
        "captionPadding": "20",
        "chartBottomMargin": "10",
        "chartLeftMargin": "20",
        "chartRightMargin": "40",
        "chartTopMargin": "10",
        "labelFontColor": "#716e6e",
        "labelFontSize": "12",
        "legendIconAlpha": "100",
        "legendIconBgAlpha": "100",
        "legendIconSides": "4",
        "legendPosition": "top",
        "theme": "fusion",
        "xAxisName": "Product Line",
        "xAxisNameFontColor": "#716e6e",
        "xAxisNameFontSize": "14",
        "yAxisName": "Revenue($)",
        "yAxisNameFontColor": "#716e6e",
        "yAxisNameFontSize": "14",
        "yAxisValueFontColor": "#716e6e",
        "yAxisValueFontSize": "12"
      },
      "data": [
        {
          "label": "Product1",
          "value": 20000
        },
        {
          "label": "Product2",
          "value": 22000
        },
        {
          "label": "Product3",
          "value": 32000
        }
      ]
    },
    "type": "column2d"
  },
  "dynamicBindingPathList": [
    {
      "key": "borderRadius"
    },
    {
      "key": "boxShadow"
    },
    {
      "key": "accentColor"
    },
    {
      "key": "fontFamily"
    },
    {
      "key": "customEChartConfig"
    }
  ],
  "dynamicPropertyPathList": [],
  "dynamicTriggerPathList": [],
  "flexVerticalAlignment": "start",
  "fontFamily": "{{appsmith.theme.fontFamily.appFont}}",
  "isLoading": false,
  "isVisible": true,
  "key": "p9s6gmzvzp",
  "labelOrientation": "auto",
  "leftColumn": 0,
  "minWidth": 450,
  "mobileBottomRow": 38,
  "mobileLeftColumn": 7,
  "mobileRightColumn": 31,
  "mobileTopRow": 6,
  "needsErrorInfo": true,
  "parentColumnSpace": 16.51031494140625,
  "parentId": "o2rxh0tnh6",
  "parentRowSpace": 10,
  "renderMode": "CANVAS",
  "responsiveBehavior": "fill",
  "rightColumn": 63,
  "showDataPointLabel": false,
  "topRow": 59,
  "type": "CHART_WIDGET",
  "version": 1,
  "widgetId": "5n3exkpf7r",
  "widgetName": "ChartWater",
  "xAxisName": "Product Line",
  "yAxisName": "Revenue($)"
}